<Namespace Name="System.Web.Management">
  <Metadata><Meta Name="ms.openlocfilehash" Value="cfb3eb6af2b26aee316fe72235776fa6268ce11d" /><Meta Name="ms.sourcegitcommit" Value="88014e1c5440e3df4f66ef04393854d15b1fd534" /><Meta Name="ms.translationtype" Value="MT" /><Meta Name="ms.contentlocale" Value="ja-JP" /><Meta Name="ms.lasthandoff" Value="09/05/2019" /><Meta Name="ms.locfileid" Value="70667764" /></Metadata><Docs>
    <summary><see cref="N:System.Web.Management" /> 名前空間には、Web アプリケーションの正常性を管理および監視するためのクラスおよびインターフェイスが含まれています。</summary>
    <remarks>To be added.</remarks>
  </Docs>
</Namespace>