<Namespace Name="System.Security.Authentication.ExtendedProtection">
  <Metadata><Meta Name="ms.openlocfilehash" Value="b482f98a5c4316a191cd9beb8d2d226874520920" /><Meta Name="ms.sourcegitcommit" Value="88014e1c5440e3df4f66ef04393854d15b1fd534" /><Meta Name="ms.translationtype" Value="MT" /><Meta Name="ms.contentlocale" Value="ja-JP" /><Meta Name="ms.lasthandoff" Value="09/05/2019" /><Meta Name="ms.locfileid" Value="70472808" /></Metadata><Docs>
    <summary><see cref="N:System.Security.Authentication.ExtendedProtection" /> 名前空間は、アプリケーションの拡張保護を使用した認証のサポートを提供します。</summary>
    <remarks>
      <format type="text/markdown"><![CDATA[  
  
## Remarks  
 統合 Windows 認証 (IWA) の設計では、一部の資格情報チャレンジ応答をユニバーサルにすることができます。つまり、これらを再利用または転送できます。 この特定の設計機能が必要でない場合は、少なくともターゲット固有の情報を使用してチャレンジ応答を構築し、チャネル固有の情報を使用することをお勧めします。 これにより、サービスは拡張保護を提供して、資格情報チャレンジ応答にサービス固有の情報 (サービスプロバイダー名または SPN) と、必要に応じてチャネル固有の情報 (チャネルバインディングトークンまたは CBT) を含めることができます。 資格情報の交換でこの情報を使用すると、不適切に取得された可能性がある資格情報チャレンジ応答の悪意のある使用からサービスを保護することができます。  
  
 ]]></format>
    </remarks>
    <altmember cref="T:System.Net.TransportContext" />
    <altmember cref="N:System.Security.Authentication.ExtendedProtection.Configuration" />
  </Docs>
</Namespace>