<Namespace Name="System.Runtime.InteropServices">
  <Metadata><Meta Name="ms.openlocfilehash" Value="639ba79277b9dd31205a5d0c9d83e19965148f78" /><Meta Name="ms.sourcegitcommit" Value="88014e1c5440e3df4f66ef04393854d15b1fd534" /><Meta Name="ms.translationtype" Value="MT" /><Meta Name="ms.contentlocale" Value="ja-JP" /><Meta Name="ms.lasthandoff" Value="09/05/2019" /><Meta Name="ms.locfileid" Value="70488458" /></Metadata><Docs>
    <summary><see cref="N:System.Runtime.InteropServices" /> 名前空間は、COM 相互運用サービスとプラットフォーム呼び出しサービスをサポートする各種メンバーを提供します。 これらのサービスに慣れていない場合は、「<see href="https://docs.microsoft.com/dotnet/framework/interop/index">アンマネージ コードとの相互運用</see>」をご覧ください。</summary>
    <remarks>
      <format type="text/markdown"><![CDATA[  
  
## Remarks  
 この名前空間のメンバーは、次の表に示すように、いくつかのカテゴリの機能を提供します。 属性は、構造の配置方法や文字列の表現方法など、マーシャリングの動作を制御します。 最も重要な属性は<xref:System.Runtime.InteropServices.DllImportAttribute>です。これは、アンマネージ api にアクセスするためのプラットフォーム呼び出し<xref:System.Runtime.InteropServices.MarshalAsAttribute>メソッドを定義するために使用します。また、は、マネージメモリとアンマネージメモリの間でデータをマーシャリングする方法を指定するために使用します。  
  
 ]]></format>
    </remarks>
  </Docs>
</Namespace>